ceilopyter/__init__.py
ceilopyter/ceilo.py
ceilopyter/ceilo_raw.py
ceilopyter/common.py
ceilopyter/noise.py
ceilopyter/py.typed
ceilopyter/utils.py
ceilopyter/version.py
ceilopyter/instruments/chm15k.py
ceilopyter/instruments/cl31.py
ceilopyter/instruments/cl51.py
ceilopyter/instruments/cl61.py
ceilopyter/instruments/cs135.py
ceilopyter/instruments/ct25k.py
ceilopyter/instruments/ld40.py
ceilopyter/readers/read_cl.py
ceilopyter/readers/read_cs.py
ceilopyter/readers/read_ct.py
ceilopyter-0.2.0.dist-info/METADATA
ceilopyter-0.2.0.dist-info/WHEEL
ceilopyter-0.2.0.dist-info/licenses/LICENSE
ceilopyter-0.2.0.dist-info/RECORD
