Metadata-Version: 2.4
Name: ceilopyter
Version: 0.2.0
Summary: Read ceilometer data
Project-URL: Homepage, https://github.com/actris-cloudnet/ceilopyter
Project-URL: Issues, https://github.com/actris-cloudnet/ceilopyter/issues
Author-email: Tuomas Siipola <tuomas.siipola@fmi.fi>
License-File: LICENSE
Classifier: Development Status :: 3 - Alpha
Classifier: Intended Audience :: Science/Research
Classifier: License :: OSI Approved :: MIT License
Classifier: Operating System :: OS Independent
Classifier: Programming Language :: Python :: 3
Classifier: Topic :: Scientific/Engineering :: Atmospheric Science
Requires-Python: >=3.10
Requires-Dist: netcdf4
Requires-Dist: numpy
Provides-Extra: dev
Requires-Dist: pre-commit; extra == 'dev'
Requires-Dist: release-version; extra == 'dev'
Provides-Extra: test
Requires-Dist: mypy; extra == 'test'
Requires-Dist: pytest; extra == 'test'
